{
  "$schema": "https://adaptivecards.io/schemas/adaptive-card.json",
  "type": "AdaptiveCard",
  "version": "1.0.0",
  "body": [
    {
      "type": "Input.Time",
      "id": "time1",
      "placeholder": "time input"
    },
    {
      "type": "Input.Time",
      "id": "time2",
      "value": "15:23"
    },
    {
      "type": "Input.Time",
      "id": "time3",
      "value": "04:23"
    },
    {
      "type": "Input.Time",
      "id": "time4",
      "value": "4:23",
      "placeholder": "you should not see default value"
    }
  ],
  "actions": [
    {
      "type": "Action.Submit",
      "title": "Submit"
    }
  ]  
}
